flag_slurper/__init__.py
flag_slurper/__main__.py
flag_slurper/autopwn.py
flag_slurper/cli.py
flag_slurper/config.py
flag_slurper/credentials.py
flag_slurper/dns.py
flag_slurper/files.py
flag_slurper/models.py
flag_slurper/notes.py
flag_slurper/project.py
flag_slurper/remote.py
flag_slurper/services.py
flag_slurper/teams.py
flag_slurper/utils.py
flag_slurper/autolib/__init__.py
flag_slurper/autolib/exploit.py
flag_slurper/autolib/governor.py
flag_slurper/autolib/models.py
flag_slurper/autolib/post.py
flag_slurper/autolib/protocols.py
flag_slurper/autolib/service.py
flag_slurper/autolib/utils.py
tests/__init__.py
tests/conftest.py
tests/response_mocks.py
tests/test_autopwn.py
tests/test_cli.py
tests/test_config.py
tests/test_credentials.py
tests/test_dns.py
tests/test_files.py
tests/test_models.py
tests/test_notes.py
tests/test_project.py
tests/test_utils.py
tests/autolib/__init__.py
tests/autolib/conftest.py
tests/autolib/test_exploit.py
tests/autolib/test_governor.py
tests/autolib/test_models.py
tests/autolib/test_post.py
tests/autolib/test_protocols.py
tests/autolib/test_service.py
tests/autolib/test_utils.py
flag_slurper-0.9.0.dist-info/LICENSE
flag_slurper-0.9.0.dist-info/METADATA
flag_slurper-0.9.0.dist-info/WHEEL
flag_slurper-0.9.0.dist-info/entry_points.txt
flag_slurper-0.9.0.dist-info/top_level.txt
flag_slurper-0.9.0.dist-info/RECORD
