Metadata-Version: 2.1
Name: flag-slurper
Version: 0.9.0
Summary: Tool for getting flags from CDC machines
Home-page: UNKNOWN
Author: Matt Gerst
Author-email: mattgerst@gmail.com
License: MIT
Platform: UNKNOWN
Classifier: Development Status :: 1 - Planning
Classifier: Programming Language :: Python :: 3.5
Classifier: Programming Language :: Python :: 3.6
Classifier: License :: OSI Approved :: MIT License
Requires-Dist: requests (>=2.20.0)
Requires-Dist: click (==6.7)
Requires-Dist: pyyaml (>=4.2b1)
Requires-Dist: schema (==0.6.7)
Requires-Dist: jinja2 (==2.10.1)
Requires-Dist: peewee (==3.9.5)
Requires-Dist: terminaltables (==3.1.0)
Requires-Dist: dnspython (==1.15.0)
Requires-Dist: Faker (==1.0.7)
Provides-Extra: dev
Requires-Dist: bumpversion (==0.5.3) ; extra == 'dev'
Requires-Dist: twine (==1.10.0) ; extra == 'dev'
Provides-Extra: docs
Requires-Dist: sphinx ; extra == 'docs'
Requires-Dist: sphinx-autobuild ; extra == 'docs'
Requires-Dist: sphinx-rtd-theme ; extra == 'docs'
Provides-Extra: parallel
Requires-Dist: psycopg2-binary (==2.7.4) ; extra == 'parallel'
Provides-Extra: remote
Requires-Dist: paramiko (==2.6.0) ; extra == 'remote'
Provides-Extra: tests
Requires-Dist: pytest (==3.4.2) ; extra == 'tests'
Requires-Dist: pytest-cov (==2.5.1) ; extra == 'tests'
Requires-Dist: pytest-sugar (==0.9.1) ; extra == 'tests'
Requires-Dist: pytest-mock (==1.7.1) ; extra == 'tests'
Requires-Dist: tox (==2.9.1) ; extra == 'tests'
Requires-Dist: vcrpy (==1.11.1) ; extra == 'tests'
Requires-Dist: responses (==0.8.1) ; extra == 'tests'
Requires-Dist: pretend (==1.0.8) ; extra == 'tests'
Requires-Dist: hypothesis (==3.57.0) ; extra == 'tests'
